spellchecker/__init__.py
spellchecker/info.py
spellchecker/py.typed
spellchecker/spellchecker.py
spellchecker/utils.py
spellchecker/resources/ar.json.gz
spellchecker/resources/de.json.gz
spellchecker/resources/en.json.gz
spellchecker/resources/es.json.gz
spellchecker/resources/eu.json.gz
spellchecker/resources/fr.json.gz
spellchecker/resources/it.json.gz
spellchecker/resources/lv.json.gz
spellchecker/resources/nl.json.gz
spellchecker/resources/pt.json.gz
spellchecker/resources/ru.json.gz
pyspellchecker-0.8.0.dist-info/LICENSE
pyspellchecker-0.8.0.dist-info/METADATA
pyspellchecker-0.8.0.dist-info/WHEEL
pyspellchecker-0.8.0.dist-info/top_level.txt
pyspellchecker-0.8.0.dist-info/RECORD
