Metadata-Version: 2.1
Name: pyspellchecker
Version: 0.8.0
Summary: Pure python spell checker based on work by Peter Norvig
Author-email: Tyler Barrus <barrust@gmail.com>
License: MIT
Project-URL: homepage, https://github.com/barrust/pyspellchecker
Project-URL: bug-tracker, https://github.com/barrust/pyspellchecker/issues
Project-URL: documentation, https://pyspellchecker.readthedocs.io/
Keywords: python,spelling,natural language processing,nlp,typo,checker
Classifier: Development Status :: 5 - Production/Stable
Classifier: Intended Audience :: Developers
Classifier: Intended Audience :: Information Technology
Classifier: Intended Audience :: Science/Research
Classifier: Topic :: Software Development :: Libraries
Classifier: Topic :: Utilities
Classifier: License :: OSI Approved
Classifier: License :: OSI Approved :: MIT License
Classifier: Programming Language :: Python
Classifier: Programming Language :: Python :: 3
Classifier: Programming Language :: Python :: 3.6
Classifier: Programming Language :: Python :: 3.7
Classifier: Programming Language :: Python :: 3.8
Classifier: Programming Language :: Python :: 3.9
Classifier: Programming Language :: Python :: 3.10
Classifier: Programming Language :: Python :: 3.11
Classifier: Programming Language :: Python :: 3.12
Requires-Python: >=3.6
License-File: LICENSE
